pycard_validate-1.0.0.dist-info/METADATA
pycard_validate-1.0.0.dist-info/RECORD
pycard_validate-1.0.0.dist-info/WHEEL
pycard_validate-1.0.0.dist-info/entry_points.txt
pycard_validate-1.0.0.dist-info/top_level.txt
pycardvalidator/__init__.py
pycardvalidator/__main__.py
pycardvalidator/validator.py
pycardvalidator/algorithm/__init__.py
pycardvalidator/algorithm/luhn.py
pycardvalidator/filter/__init__.py
pycardvalidator/filter/filter_default.py
tests/__init__.py
tests/test_filter.py
tests/test_validator.py
