Metadata-Version: 2.1
Name: pycard-validate
Version: 1.0.0
Summary: Blazing Fast Credit Card number validator using Luhn Algorithm
Home-page: https://github.com/subhajeet2107/pycard-validate
Author: Subhajeet Dey
Author-email: subhajeet2107@gmail.com
License: MIT License
Platform: UNKNOWN
Requires-Dist: pytest
Requires-Dist: six
